essencia_app/__init__.py
essencia_app/abstract.py
essencia_app/context.py
essencia_app/endpoints/__init__.py
essencia_app/endpoints/handlers/__init__.py
essencia_app/endpoints/handlers/base.py
essencia_app/endpoints/html.py
essencia_app/endpoints/json.py
essencia_app/managers.py
essencia_app/middlewares.py
essencia_app/models.py
essencia_app/routes.py
essencia_app/settings.py
essencia_app/static/css/style.css
essencia_app/templates/general.html
essencia_app/templates/index.html
essencia_app/utils/__init__.py
essencia_app/utils/elements.py
essencia_app/utils/render.py
essencia_app/utils/select.py
essencia_app-0.1.0.dist-info/LICENSE
essencia_app-0.1.0.dist-info/WHEEL
essencia_app-0.1.0.dist-info/METADATA
essencia_app-0.1.0.dist-info/RECORD
