Metadata-Version: 2.1
Name: essencia-app
Version: 0.1.0
Summary: MIT
License: MIT
Author: arantesdv
Author-email: arantesdv@me.com
Requires-Python: >=3.7,<4.0
Classifier: License :: OSI Approved :: MIT License
Classifier: Programming Language :: Python :: 3
Classifier: Programming Language :: Python :: 3.7
Classifier: Programming Language :: Python :: 3.8
Classifier: Programming Language :: Python :: 3.9
Requires-Dist: deta (>=0.8,<0.9)
Requires-Dist: starlette (>=0.14.2,<0.15.0)
